PathWise/A_Star.py
PathWise/BFS.py
PathWise/DFS.py
PathWise/Helper.py
PathWise/UCS.py
PathWise/__init__.py
pathwise-1.2.0.dist-info/licenses/LICENSE
pathwise-1.2.0.dist-info/METADATA
pathwise-1.2.0.dist-info/WHEEL
pathwise-1.2.0.dist-info/top_level.txt
pathwise-1.2.0.dist-info/RECORD
