Metadata-Version: 2.4
Name: PathWise
Version: 1.2.0
Summary: A Python package implementing various search algorithms for maze solving
Home-page: https://github.com/MahdiJaffery/PathWise
Author: Mahdi Jaffery
Author-email: mahdijaffri5@gmail.com
Project-URL: Source, https://github.com/MahdiJaffery/PathWise
Keywords: maze search algorithms pathfinding BFS DFS A* UCS
Classifier: Programming Language :: Python :: 3
Classifier: License :: OSI Approved :: MIT License
Classifier: Operating System :: OS Independent
Classifier: Intended Audience :: Education
Classifier: Intended Audience :: Science/Research
Classifier: Topic :: Scientific/Engineering :: Artificial Intelligence
Requires-Python: >=3.6
License-File: LICENSE
Requires-Dist: numpy>=1.19.0
Dynamic: author
Dynamic: author-email
Dynamic: classifier
Dynamic: description
Dynamic: description-content-type
Dynamic: home-page
Dynamic: keywords
Dynamic: license-file
Dynamic: project-url
Dynamic: requires-dist
Dynamic: requires-python
Dynamic: summary
